test_infinity_stones/__init__.py
test_infinity_stones/auth/__init__.py
test_infinity_stones/auth/authenticator.py
test_infinity_stones/auth/config.py
test_infinity_stones/auth/errors.py
test_infinity_stones/auth/user_auth_schemas.py
test_infinity_stones/core/__init__.py
test_infinity_stones/core/local_cache.py
test_infinity_stones/network_router/__init__.py
test_infinity_stones/network_router/http_exception.py
test_infinity_stones/network_router/http_request.py
test_infinity_stones/network_router/http_response.py
test_infinity_stones/network_router/http_types.py
test_infinity_stones/network_router/router.py
test_infinity_stones/network_router/utils/__init__.py
test_infinity_stones/network_router/utils/url_builder.py
test_infinity_stones/redis_client/__init__.py
test_infinity_stones/redis_client/redis_client.py
test_infinity_stones-0.0.14.dist-info/LICENSE
test_infinity_stones-0.0.14.dist-info/METADATA
test_infinity_stones-0.0.14.dist-info/WHEEL
test_infinity_stones-0.0.14.dist-info/top_level.txt
test_infinity_stones-0.0.14.dist-info/RECORD
